barrel_shifter/barrel_shifter.sv
// 23 bit mantissa + guard + round + sticky
module barrel_shifter #(
    parameter EXPONENT_WIDTH        = 8,
    parameter MANTISSA_BIT_WIDTH    = 23 
)(
    input logic                             clk_i,
    input logic                             rst_n_i,
    input logic [EXPONENT_WIDTH-1:0]        exponent_difference_i,
    input logic [MANTISSA_BIT_WIDTH-1:0]    mantissa_in_i,
    input logic                             mantissa_in_valid_i,

    output logic [MANTISSA_BIT_WIDTH-1:0]   mantissa_out_o,
    output logic                            mantissa_out_valid_o,
    output logic                            guard_bit_o,
    output logic                            round_bit_o,
    output logic                            sticky_bit_o
);

    localparam int EXT_WIDTH = 2*MANTISSA_BIT_WIDTH + 2;
    localparam int PAD_WIDTH = MANTISSA_BIT_WIDTH + 2;
    localparam int SHIFT_WIDTH = $clog2(PAD_WIDTH+1);

    logic [EXT_WIDTH-1:0]extended;
    logic [EXT_WIDTH-1:0]shifted;
    logic [SHIFT_WIDTH-1:0]shift_amt_clamped;
    logic is_exponent_greater;

    always_comb begin
        is_exponent_greater = exponent_difference_i >= EXPONENT_WIDTH'(PAD_WIDTH);
        shift_amt_clamped = (is_exponent_greater)
                            ? SHIFT_WIDTH'(PAD_WIDTH)
                            : SHIFT_WIDTH'(exponent_difference_i);
        extended = {mantissa_in_i, {PAD_WIDTH{1'b0}}};
        shifted = extended >> shift_amt_clamped;
    end

    always_ff @(posedge clk_i or negedge rst_n_i) begin
        if(!rst_n_i) begin
            guard_bit_o          <= 1'b0;
            round_bit_o          <= 1'b0;
            sticky_bit_o         <= 1'b0;
            mantissa_out_o       <= {MANTISSA_BIT_WIDTH{1'b0}};
            mantissa_out_valid_o <= 1'b0;
        end 
        else if(is_exponent_greater) begin
            mantissa_out_o            <=  {MANTISSA_BIT_WIDTH{1'b0}};
            {guard_bit_o,round_bit_o} <=  2'b00;
            sticky_bit_o              <= |mantissa_in_i;
            mantissa_out_valid_o      <=  mantissa_in_valid_i;
        end 
        else begin
            mantissa_out_o            <=  shifted[47:25];
            {guard_bit_o,round_bit_o} <=  {shifted[24],shifted[23]};
            sticky_bit_o              <= |shifted[22:0];
            mantissa_out_valid_o      <=  mantissa_in_valid_i;
        end
    end

endmodule

barrel_shifter/tb_barrel_shift.sv
module tb_barrel_shifter;

parameter EXPONENT_WIDTH = 8;
parameter STICKY_BIT_WIDTH = 1 << EXPONENT_WIDTH;
parameter MANTISSA_BIT_WIDTH = 23;

logic clk;
logic rst_n;
logic [EXPONENT_WIDTH-1:0]exponent_difference;
logic [MANTISSA_BIT_WIDTH-1:0]mantissa_in;
logic mantissa_in_valid;

logic [MANTISSA_BIT_WIDTH-1:0]mantissa_out;
logic mantissa_out_valid;
logic guard_bit;
logic round_bit;
logic sticky_bit;

localparam int TB_EXPONENT_WIDTH = 8;
localparam int TB_MANTISSA_BIT_WIDTH = 23;

barrel_shifter #(
    .EXPONENT_WIDTH(TB_EXPONENT_WIDTH),
    .MANTISSA_BIT_WIDTH(TB_MANTISSA_BIT_WIDTH)
) DUT (
    .clk_i(clk),
    .rst_n_i(rst_n),
    .exponent_difference_i(exponent_difference),
    .mantissa_in_i(mantissa_in),
    .mantissa_in_valid_i(mantissa_in_valid),
    
    .mantissa_out_o(mantissa_out),
    .mantissa_out_valid_o(mantissa_out_valid),
    .guard_bit_o(guard_bit),
    .round_bit_o(round_bit),
    .sticky_bit_o(sticky_bit)
);

always #5 clk = ~clk;

initial begin
    clk = 0;
    rst_n = 1;
end

initial begin
    #5;
    rst_n = 0;

    #5 rst_n = 1;

       @(negedge clk)
       mantissa_in = 23'b000_0000_0000_0000_0000_0001;
       exponent_difference = 0;

       @(negedge clk)
       mantissa_in = 23'b111_1111_1111_1111_1111_1111;
       exponent_difference = 0;

       @(negedge clk)
       mantissa_in = 23'b100_0000_0000_0000_0000_0000;
       exponent_difference = 1;

       @(negedge clk)
       mantissa_in = 23'b000_0000_0000_0000_0000_0001;
       exponent_difference = 1;

       @(negedge clk)
       mantissa_in = 23'b000_0000_0000_0000_0000_0001;
       exponent_difference = 2;

       @(negedge clk)
       mantissa_in = 23'b000_0000_0000_0000_0000_0001;
       exponent_difference = 3;

       @(negedge clk)
       mantissa_in = 23'b000_0000_0000_0000_0000_0011;
       exponent_difference = 1;

       @(negedge clk)
       mantissa_in = 23'b100_0000_0000_0000_0000_0000;
       exponent_difference = 22;

       @(negedge clk)
       mantissa_in = 23'b100_0000_0000_0000_0000_0000;
       exponent_difference = 23;

       @(negedge clk)
       mantissa_in = 23'b100_0000_0000_0000_0000_0000;
       exponent_difference = 24;

       @(negedge clk)
       mantissa_in = 23'b100_0000_0000_0000_0000_0000;
       exponent_difference = 25;

       @(negedge clk)
       mantissa_in = 23'b000_0000_0000_0000_0000_0001;
       exponent_difference = 25;

       @(negedge clk)
       mantissa_in = 23'b000_0000_0000_0000_0000_0000;
       exponent_difference = 200;

       @(negedge clk)
       mantissa_in = 23'b100_0000_0000_0000_0000_0000;
       exponent_difference = 255;

       @(negedge clk)
       mantissa_in = 23'b100_0000_0000_0000_0000_0000;
       exponent_difference = 21;

       @(negedge clk)
       mantissa_in = 23'b100_0000_0000_0000_0000_0000;
       exponent_difference = 22;

       @(negedge clk)
       mantissa_in = 23'b100_0000_0000_0000_0000_0000;
       exponent_difference = 23;

       @(negedge clk)
       mantissa_in = 23'b100_0000_0000_0000_0000_0000;
       exponent_difference = 24;

       @(negedge clk)
       mantissa_in = 23'b100_0000_0000_0000_0000_0000;
       exponent_difference = 25;

       @(negedge clk)
       mantissa_in = 23'b100_0000_0000_0000_0000_0000;
       exponent_difference = 26;

       @(negedge clk)
       mantissa_in = 23'b000_0000_0000_0000_0000_0000;
       exponent_difference = 25;

       @(negedge clk)
       mantissa_in = 23'b000_0000_0000_0000_0000_0001;
       exponent_difference = 255;

       @(negedge clk)
       mantissa_in = 23'b100_0000_0000_0000_0000_0000;
       exponent_difference = 128;
    #100;
    $finish;
end

initial begin
    $dumpfile("wave.vcd");
    $dumpvars(0, tb_barrel_shifter);
end

// initial begin
//     $monitor("mantissa_out = %b | guard = %b | round = %b | sticky = %b",mantissa_out,guard_bit,round_bit,sticky_bit);
// end


endmodule

barrel_shifter/waveform/wave.vcd
$version Generated by VerilatedVcd $end
$timescale 1ps $end
 $scope module TOP $end
  $scope module tb_barrel_shifter $end
   $var wire 32 2 EXPONENT_WIDTH [31:0] $end
   $var wire 32 3 STICKY_BIT_WIDTH [31:0] $end
   $var wire 32 4 MANTISSA_BIT_WIDTH [31:0] $end
   $var wire 1 ( clk $end
   $var wire 1 ) rst_n $end
   $var wire 8 * exponent_difference [7:0] $end
   $var wire 23 + mantissa_in [22:0] $end
   $var wire 1 5 mantissa_in_valid $end
   $var wire 23 # mantissa_out [22:0] $end
   $var wire 1 $ mantissa_out_valid $end
   $var wire 1 % guard_bit $end
   $var wire 1 & round_bit $end
   $var wire 1 ' sticky_bit $end
   $var wire 32 6 TB_EXPONENT_WIDTH [31:0] $end
   $var wire 32 7 TB_MANTISSA_BIT_WIDTH [31:0] $end
   $scope module DUT $end
    $var wire 32 2 EXPONENT_WIDTH [31:0] $end
    $var wire 32 4 MANTISSA_BIT_WIDTH [31:0] $end
    $var wire 1 ( clk_i $end
    $var wire 1 ) rst_n_i $end
    $var wire 8 * exponent_difference_i [7:0] $end
    $var wire 23 + mantissa_in_i [22:0] $end
    $var wire 1 5 mantissa_in_valid_i $end
    $var wire 23 # mantissa_out_o [22:0] $end
    $var wire 1 $ mantissa_out_valid_o $end
    $var wire 1 % guard_bit_o $end
    $var wire 1 & round_bit_o $end
    $var wire 1 ' sticky_bit_o $end
    $var wire 32 8 EXT_WIDTH [31:0] $end
    $var wire 32 9 PAD_WIDTH [31:0] $end
    $var wire 32 : SHIFT_WIDTH [31:0] $end
    $var wire 48 , extended [47:0] $end
    $var wire 48 . shifted [47:0] $end
    $var wire 5 0 shift_amt_clamped [4:0] $end
    $var wire 1 1 is_exponent_greater $end
   $upscope $end
  $upscope $end
 $upscope $end
$enddefinitions $end


#0
b00000000000000000000000 #
0$
0%
0&
0'
0(
1)
b00000000 *
b00000000000000000000000 +
b000000000000000000000000000000000000000000000000 ,
b000000000000000000000000000000000000000000000000 .
b00000 0
01
b00000000000000000000000000001000 2
b00000000000000000000000100000000 3
b00000000000000000000000000010111 4
05
b00000000000000000000000000001000 6
b00000000000000000000000000010111 7
b00000000000000000000000000110000 8
b00000000000000000000000000011001 9
b00000000000000000000000000000101 :
#5
1(
0)
#10
0(
1)
#15
1(
#20
0(
b00000000000000000000001 +
b000000000000000000000010000000000000000000000000 ,
b000000000000000000000010000000000000000000000000 .
#25
b00000000000000000000001 #
1(
#30
0(
b11111111111111111111111 +
b111111111111111111111110000000000000000000000000 ,
b111111111111111111111110000000000000000000000000 .
#35
b11111111111111111111111 #
1(
#40
0(
b00000001 *
b10000000000000000000000 +
b100000000000000000000000000000000000000000000000 ,
b010000000000000000000000000000000000000000000000 .
b00001 0
#45
b01000000000000000000000 #
1(
#50
0(
b00000000000000000000001 +
b000000000000000000000010000000000000000000000000 ,
b000000000000000000000001000000000000000000000000 .
#55
b00000000000000000000000 #
1%
1(
#60
0(
b00000010 *
b000000000000000000000000100000000000000000000000 .
b00010 0
#65
0%
1&
1(
#70
0(
b00000011 *
b000000000000000000000000010000000000000000000000 .
b00011 0
#75
0&
1'
1(
#80
0(
b00000001 *
b00000000000000000000011 +
b000000000000000000000110000000000000000000000000 ,
b000000000000000000000011000000000000000000000000 .
b00001 0
#85
b00000000000000000000001 #
1%
0'
1(
#90
0(
b00010110 *
b10000000000000000000000 +
b100000000000000000000000000000000000000000000000 ,
b000000000000000000000010000000000000000000000000 .
b10110 0
#95
0%
1(
#100
0(
b00010111 *
b000000000000000000000001000000000000000000000000 .
b10111 0
#105
b00000000000000000000000 #
1%
1(
#110
0(
b00011000 *
b000000000000000000000000100000000000000000000000 .
b11000 0
#115
0%
1&
1(
#120
0(
b00011001 *
b000000000000000000000000010000000000000000000000 .
b11001 0
11
#125
0&
1'
1(
#130
0(
b00000000000000000000001 +
b000000000000000000000010000000000000000000000000 ,
b000000000000000000000000000000000000000000000001 .
#135
1(
#140
0(
b11001000 *
b00000000000000000000000 +
b000000000000000000000000000000000000000000000000 ,
b000000000000000000000000000000000000000000000000 .
#145
0'
1(
#150
0(
b11111111 *
b10000000000000000000000 +
b100000000000000000000000000000000000000000000000 ,
b000000000000000000000000010000000000000000000000 .
#155
1'
1(
#160
0(
b00010101 *
b000000000000000000000100000000000000000000000000 .
b10101 0
01
#165
b00000000000000000000010 #
0'
1(
#170
0(
b00010110 *
b000000000000000000000010000000000000000000000000 .
b10110 0
#175
b00000000000000000000001 #
1(
#180
0(
b00010111 *
b000000000000000000000001000000000000000000000000 .
b10111 0
#185
b00000000000000000000000 #
1%
1(
#190
0(
b00011000 *
b000000000000000000000000100000000000000000000000 .
b11000 0
#195
0%
1&
1(
#200
0(
b00011001 *
b000000000000000000000000010000000000000000000000 .
b11001 0
11
#205
0&
1'
1(
#210
0(
b00011010 *
#215
1(
#220
0(
b00011001 *
b00000000000000000000000 +
b000000000000000000000000000000000000000000000000 ,
b000000000000000000000000000000000000000000000000 .
#225
0'
1(
#230
0(
b11111111 *
b00000000000000000000001 +
b000000000000000000000010000000000000000000000000 ,
b000000000000000000000000000000000000000000000001 .
#235
1'
1(
#240
0(
b10000000 *
b10000000000000000000000 +
b100000000000000000000000000000000000000000000000 ,
b000000000000000000000000010000000000000000000000 .
